hermessplitter/__init__.py
hermessplitter/functions.py
hermessplitter/main.py
hermessplitter/db/__init__.py
hermessplitter/db/db_funcs.py
hermessplitter/db/init_db.py
hermessplitter/db/tables.py
hermessplitter/db/tests/__init__.py
hermessplitter/db/tests/db_funcs_test.py
hermessplitter/fast_api/__init__.py
hermessplitter/fast_api/functions.py
hermessplitter/fast_api/main.py
hermessplitter/tests/__init__.py
hermessplitter/tests/hermes_activate_tests.py
hermessplitter/tests/test_functions.py
hermessplitter-3.2.3.dist-info/LICENSE
hermessplitter-3.2.3.dist-info/METADATA
hermessplitter-3.2.3.dist-info/WHEEL
hermessplitter-3.2.3.dist-info/top_level.txt
hermessplitter-3.2.3.dist-info/RECORD
