Metadata-Version: 2.1
Name: hermessplitter
Version: 3.2.3
Author: punchyarchy
Author-email: ksmdrmvscthny@gmail.com
License-File: LICENSE
Requires-Dist: SQLAlchemy ==1.4.29
Requires-Dist: ws-one ==1.12.41
Requires-Dist: fastapi
Requires-Dist: uvicorn
